classic/sql_storage/__init__.py
classic/sql_storage/repository.py
classic/sql_storage/transactions.py
classic/sql_storage/utils.py
classic_sql_storage-0.0.2.dist-info/LICENSE
classic_sql_storage-0.0.2.dist-info/METADATA
classic_sql_storage-0.0.2.dist-info/WHEEL
classic_sql_storage-0.0.2.dist-info/top_level.txt
classic_sql_storage-0.0.2.dist-info/RECORD
