Metadata-Version: 2.2
Name: classic-sql-storage
Version: 0.0.2
Summary: Provides primitives for contextual transactions processing with SQLALchemy and base for repository class
Home-page: https://github.com/variasov/classic_sql_storage
Author: Sergei Variasov
Author-email: variasov@gmail.com
Project-URL: Bug Tracker, https://github.com/variasov/classic_sql_storage/issues
Classifier: Programming Language :: Python :: 3.7
Classifier: License :: OSI Approved :: MIT License
Classifier: Operating System :: OS Independent
Classifier: Development Status :: 4 - Beta
Requires-Python: >=3.7
License-File: LICENSE
Requires-Dist: sqlalchemy~=1.4.23
Requires-Dist: classic-components>=1.2.0
Provides-Extra: dev
Requires-Dist: pytest~=6.2.5; extra == "dev"
Requires-Dist: pytest-cov~=2.12.1; extra == "dev"
Requires-Dist: twine~=3.4.2; extra == "dev"
Requires-Dist: build~=0.7.0; extra == "dev"
